fragment_api/__init__.py
fragment_api/client.py
fragment_api/exceptions.py
fragment_api/models.py
fragment_api/py.typed
fragment_stars_api-2.0.0.dist-info/licenses/LICENSE
fragment_stars_api-2.0.0.dist-info/METADATA
fragment_stars_api-2.0.0.dist-info/WHEEL
fragment_stars_api-2.0.0.dist-info/top_level.txt
fragment_stars_api-2.0.0.dist-info/RECORD
