Metadata-Version: 2.4
Name: fragment-stars-api
Version: 2.0.0
Summary: Python SDK for Fragment API - Buy Telegram Stars and Premium with dual commission modes (KYC/Non-KYC)
Author-email: Fragment API <support@fragment-api.com>
License: MIT
Project-URL: Homepage, https://github.com/fragment-api/fragment-stars-api
Project-URL: Documentation, https://github.com/fragment-api/fragment-stars-api#readme
Project-URL: Repository, https://github.com/fragment-api/fragment-stars-api
Project-URL: Issues, https://github.com/fragment-api/fragment-stars-api/issues
Keywords: telegram,stars,premium,fragment,ton,api,sdk,kyc,prepayment
Classifier: Development Status :: 4 - Beta
Classifier: Intended Audience :: Developers
Classifier: License :: OSI Approved :: MIT License
Classifier: Operating System :: OS Independent
Classifier: Programming Language :: Python :: 3
Classifier: Programming Language :: Python :: 3.9
Classifier: Programming Language :: Python :: 3.10
Classifier: Programming Language :: Python :: 3.11
Classifier: Programming Language :: Python :: 3.12
Classifier: Topic :: Software Development :: Libraries :: Python Modules
Classifier: Typing :: Typed
Requires-Python: >=3.9
License-File: LICENSE
Requires-Dist: requests>=2.28.0
Provides-Extra: dev
Requires-Dist: pytest>=7.0; extra == "dev"
Requires-Dist: pytest-cov>=4.0; extra == "dev"
Requires-Dist: mypy>=1.0; extra == "dev"
Requires-Dist: ruff>=0.1.0; extra == "dev"
Dynamic: license-file
